alibabacloud_polardb20170801/__init__.py
alibabacloud_polardb20170801/client.py
alibabacloud_polardb20170801/models/__init__.py
alibabacloud_polardb20170801/models/_abort_dbcluster_migration_request.py
alibabacloud_polardb20170801/models/_abort_dbcluster_migration_response.py
alibabacloud_polardb20170801/models/_abort_dbcluster_migration_response_body.py
alibabacloud_polardb20170801/models/_add_encryption_dbrole_privilege_request.py
alibabacloud_polardb20170801/models/_add_encryption_dbrole_privilege_response.py
alibabacloud_polardb20170801/models/_add_encryption_dbrole_privilege_response_body.py
alibabacloud_polardb20170801/models/_add_firewall_rules_request.py
alibabacloud_polardb20170801/models/_add_firewall_rules_response.py
alibabacloud_polardb20170801/models/_add_firewall_rules_response_body.py
alibabacloud_polardb20170801/models/_add_polar_fs_quota_request.py
alibabacloud_polardb20170801/models/_add_polar_fs_quota_response.py
alibabacloud_polardb20170801/models/_add_polar_fs_quota_response_body.py
alibabacloud_polardb20170801/models/_add_sqlrate_limiting_rules_request.py
alibabacloud_polardb20170801/models/_add_sqlrate_limiting_rules_response.py
alibabacloud_polardb20170801/models/_add_sqlrate_limiting_rules_response_body.py
alibabacloud_polardb20170801/models/_attach_application_polar_fsrequest.py
alibabacloud_polardb20170801/models/_attach_application_polar_fsresponse.py
alibabacloud_polardb20170801/models/_attach_application_polar_fsresponse_body.py
alibabacloud_polardb20170801/models/_cancel_active_operation_tasks_request.py
alibabacloud_polardb20170801/models/_cancel_active_operation_tasks_response.py
alibabacloud_polardb20170801/models/_cancel_active_operation_tasks_response_body.py
alibabacloud_polardb20170801/models/_cancel_cron_job_policy_serverless_request.py
alibabacloud_polardb20170801/models/_cancel_cron_job_policy_serverless_response.py
alibabacloud_polardb20170801/models/_cancel_cron_job_policy_serverless_response_body.py
alibabacloud_polardb20170801-6.6.4.dist-info/LICENSE
alibabacloud_polardb20170801-6.6.4.dist-info/METADATA
alibabacloud_polardb20170801-6.6.4.dist-info/WHEEL
alibabacloud_polardb20170801-6.6.4.dist-info/top_level.txt
alibabacloud_polardb20170801-6.6.4.dist-info/RECORD
